<?xml version="1.0" encoding="UTF-8"?>
<metadata xml:lang="zh"><Esri><CreaDate>20260101</CreaDate><CreaTime>18165600</CreaTime><ArcGISFormat>1.0</ArcGISFormat><SyncOnce>TRUE</SyncOnce><DataProperties><itemProps><itemLocation><linkage Sync="TRUE">file://\\FJH\M$\基础类项目\国有城镇基准地价项目\登封市城镇基准地价更新2023年\出图矢量数据\城区工程及矢量数据\矢量数据\净地库\合并\E2022</linkage><protocol Sync="TRUE">Local Area Network</protocol></itemLocation></itemProps><copyHistory><copy source="M:\基础类项目\国有城镇基准地价项目\登封市城镇基准地价更新2023年\出图矢量数据\城区工程及矢量数据\矢量数据\净地库\E2022" dest="\\FJH\M$\基础类项目\国有城镇基准地价项目\登封市城镇基准地价更新2023年\出图矢量数据\城区工程及矢量数据\矢量数据\净地库\合并\E2022" date="20231221" time="08434500"></copy></copyHistory><lineage><Process ToolSource="c:\program files (x86)\arcgis\desktop10.2\ArcToolbox\Toolboxes\Data Management Tools.tbx\CalculateField" Date="20231221" Time="085041">CalculateField E18-22 Id 2018 VB #</Process><Process ToolSource="c:\program files (x86)\arcgis\desktop10.2\ArcToolbox\Toolboxes\Data Management Tools.tbx\CalculateField" Date="20231221" Time="085059">CalculateField E18-22 Id 2019 VB #</Process><Process ToolSource="c:\program files (x86)\arcgis\desktop10.2\ArcToolbox\Toolboxes\Data Management Tools.tbx\CalculateField" Date="20231221" Time="085112">CalculateField E18-22 Id 2020 VB #</Process><Process ToolSource="c:\program files (x86)\arcgis\desktop10.2\ArcToolbox\Toolboxes\Data Management Tools.tbx\CalculateField" Date="20231221" Time="085124">CalculateField E18-22 Id 2021 VB #</Process><Process ToolSource="c:\program files (x86)\arcgis\desktop10.2\ArcToolbox\Toolboxes\Data Management Tools.tbx\CalculateField" Date="20231221" Time="085136">CalculateField E18-22 Id 2022 VB #</Process><Process ToolSource="c:\program files (x86)\arcgis\desktop10.2\ArcToolbox\Toolboxes\Data Management Tools.tbx\CalculateField" Date="20231221" Time="090532">CalculateField E18-22 受让方 "河南汉华嘉拓文化发展有限公司" VB #</Process><Process ToolSource="c:\program files (x86)\arcgis\desktop10.2\ArcToolbox\Toolboxes\Data Management Tools.tbx\CalculateField" Date="20231221" Time="090550">CalculateField E18-22 位置 "登封市环山旅游公路以东、颍河路以南、南环二路以北" VB #</Process><Process ToolSource="c:\program files (x86)\arcgis\desktop10.2\ArcToolbox\Toolboxes\Data Management Tools.tbx\CalculateField" Date="20231221" Time="093213">CalculateField E18-22 用途 "住宅" VB #</Process><Process ToolSource="c:\program files (x86)\arcgis\desktop10.2\ArcToolbox\Toolboxes\Data Management Tools.tbx\CalculateField" Date="20231221" Time="093248">CalculateField E18-22 用途 "住宅兼容商业" VB #</Process><Process ToolSource="c:\program files (x86)\arcgis\desktop10.2\ArcToolbox\Toolboxes\Data Management Tools.tbx\CalculateField" Date="20231221" Time="093344">CalculateField E18-22 用途 "工业" VB #</Process><Process ToolSource="c:\program files (x86)\arcgis\desktop10.2\ArcToolbox\Toolboxes\Data Management Tools.tbx\CalculateField" Date="20231221" Time="093437">CalculateField E18-22 用途 "商业" VB #</Process><Process ToolSource="c:\program files (x86)\arcgis\desktop10.2\ArcToolbox\Toolboxes\Data Management Tools.tbx\CalculateField" Date="20231221" Time="093758">CalculateField E18-22 用_途 "批发零售用地" VB #</Process><Process ToolSource="c:\program files (x86)\arcgis\desktop10.2\ArcToolbox\Toolboxes\Data Management Tools.tbx\CalculateField" Date="20231221" Time="093808">CalculateField E18-22 成交单价万 43 VB #</Process><Process ToolSource="c:\program files (x86)\arcgis\desktop10.2\ArcToolbox\Toolboxes\Data Management Tools.tbx\CalculateField" Date="20231221" Time="093822">CalculateField E18-22 用途 "商业" VB #</Process><Process ToolSource="c:\program files (x86)\arcgis\desktop10.2\ArcToolbox\Toolboxes\Data Management Tools.tbx\CalculateField" Date="20231221" Time="093953">CalculateField E18-22 用途 "商业" VB #</Process><Process ToolSource="c:\program files (x86)\arcgis\desktop10.2\ArcToolbox\Toolboxes\Data Management Tools.tbx\CalculateField" Date="20231221" Time="094008">CalculateField E18-22 用_途 "批发零售用地" VB #</Process><Process ToolSource="c:\program files (x86)\arcgis\desktop10.2\ArcToolbox\Toolboxes\Data Management Tools.tbx\CalculateField" Date="20231221" Time="094329">CalculateField E18-22 用途 "住宅" VB #</Process><Process ToolSource="c:\program files (x86)\arcgis\desktop10.2\ArcToolbox\Toolboxes\Data Management Tools.tbx\CalculateField" Date="20231221" Time="094338">CalculateField E18-22 成交单价万 126.51 VB #</Process><Process ToolSource="c:\program files (x86)\arcgis\desktop10.2\ArcToolbox\Toolboxes\Data Management Tools.tbx\CalculateField" Date="20231221" Time="094840">CalculateField E18-22 成交单价万 27.5 VB #</Process><Process ToolSource="c:\program files (x86)\arcgis\desktop10.2\ArcToolbox\Toolboxes\Data Management Tools.tbx\CalculateField" Date="20231221" Time="094913">CalculateField E18-22 用途 "物流仓储" VB #</Process><Process ToolSource="c:\program files (x86)\arcgis\desktop10.2\ArcToolbox\Toolboxes\Data Management Tools.tbx\CalculateField" Date="20231221" Time="095057">CalculateField E18-22 成交价万元 [成交单价万] VB #</Process><Process ToolSource="c:\program files (x86)\arcgis\desktop10.2\ArcToolbox\Toolboxes\Data Management Tools.tbx\CalculateField" Date="20231221" Time="095200">CalculateField E18-22 年份 "[Id] &amp;"年"" VB #</Process><Process ToolSource="c:\program files (x86)\arcgis\desktop10.2\ArcToolbox\Toolboxes\Data Management Tools.tbx\CalculateField" Date="20240102" Time="104757">CalculateField E18-22 成交价万元 28 VB #</Process><Process ToolSource="c:\program files (x86)\arcgis\desktop10.2\ArcToolbox\Toolboxes\Data Management Tools.tbx\CalculateField" Date="20240102" Time="105024">CalculateField E18-22 用途 "公共" VB #</Process><Process ToolSource="c:\program files (x86)\arcgis\desktop10.2\ArcToolbox\Toolboxes\Data Management Tools.tbx\CalculateField" Date="20240102" Time="114025">CalculateField E18-22 成交价万元 263 VB #</Process><Process ToolSource="c:\program files (x86)\arcgis\desktop10.2\ArcToolbox\Toolboxes\Data Management Tools.tbx\CalculateField" Date="20240103" Time="183226">CalculateField E18-22 成交价万元 89.06 VB #</Process><Process ToolSource="c:\program files (x86)\arcgis\desktop10.2\ArcToolbox\Toolboxes\Data Management Tools.tbx\CalculateField" Date="20240108" Time="161625">CalculateField E18-23 年份 "2023年" VB #</Process><Process ToolSource="c:\program files (x86)\arcgis\desktop10.2\ArcToolbox\Toolboxes\Data Management Tools.tbx\CalculateField" Date="20240108" Time="161657">CalculateField E18-23 成交价万元 [成交单价万] VB #</Process><Process ToolSource="c:\program files (x86)\arcgis\desktop10.2\ArcToolbox\Toolboxes\Data Management Tools.tbx\CalculateField" Date="20240108" Time="161816">CalculateField E18-23 XH [序号] VB #</Process><Process ToolSource="c:\program files (x86)\arcgis\desktop10.2\ArcToolbox\Toolboxes\Data Management Tools.tbx\CalculateField" Date="20240108" Time="161905">CalculateField E18-23 OID_ 999 VB #</Process><Process ToolSource="c:\program files (x86)\arcgis\desktop10.2\ArcToolbox\Toolboxes\Data Management Tools.tbx\CalculateField" Date="20240108" Time="170657">CalculateField 城区样点 用途4 [用途] VB #</Process><Process ToolSource="c:\program files (x86)\arcgis\desktop10.2\ArcToolbox\Toolboxes\Data Management Tools.tbx\CalculateField" Date="20240108" Time="170710">CalculateField 城区样点 用途4 "工业" VB #</Process><Process ToolSource="c:\program files (x86)\arcgis\desktop10.2\ArcToolbox\Toolboxes\Data Management Tools.tbx\CalculateField" Date="20240108" Time="170726">CalculateField 城区样点 用途4 "住宅" VB #</Process><Process ToolSource="c:\program files (x86)\arcgis\desktop10.2\ArcToolbox\Toolboxes\Data Management Tools.tbx\CalculateField" Date="20240108" Time="175322">CalculateField 城区样点 容积率2 Right( [容积率],3 ) VB #</Process><Process ToolSource="c:\program files (x86)\arcgis\desktop10.2\ArcToolbox\Toolboxes\Data Management Tools.tbx\CalculateField" Date="20240108" Time="175341">CalculateField 城区样点 容积率2 Right( [容积率],3 ) VB #</Process><Process ToolSource="c:\program files (x86)\arcgis\desktop10.2\ArcToolbox\Toolboxes\Data Management Tools.tbx\CalculateField" Date="20240108" Time="175402">CalculateField 城区样点 容积率2 Right( [容积率],2 ) VB #</Process><Process ToolSource="c:\program files (x86)\arcgis\desktop10.2\ArcToolbox\Toolboxes\Data Management Tools.tbx\CalculateField" Date="20240108" Time="175410">CalculateField 城区样点 容积率2 Right( [容积率],1 ) VB #</Process><Process ToolSource="c:\program files (x86)\arcgis\desktop10.2\ArcToolbox\Toolboxes\Data Management Tools.tbx\CalculateField" Date="20240108" Time="175422">CalculateField 城区样点 容积率2 1 VB #</Process><Process ToolSource="c:\program files (x86)\arcgis\desktop10.2\ArcToolbox\Toolboxes\Data Management Tools.tbx\CalculateField" Date="20240109" Time="090629">CalculateField 城区样点 权利人 Mid( [受让方],2,6 ) VB #</Process><Process ToolSource="c:\program files (x86)\arcgis\desktop10.2\ArcToolbox\Toolboxes\Data Management Tools.tbx\CalculateField" Date="20240109" Time="090647">CalculateField 城区样点 权利人 Mid( [受让方],3,6 ) VB #</Process><Process ToolSource="c:\program files (x86)\arcgis\desktop10.2\ArcToolbox\Toolboxes\Data Management Tools.tbx\CalculateField" Date="20240109" Time="090714">CalculateField 城区样点 权利人 Mid( [受让方],3,4 ) VB #</Process><Process ToolSource="c:\program files (x86)\arcgis\desktop10.2\ArcToolbox\Toolboxes\Data Management Tools.tbx\CalculateField" Date="20240109" Time="090810">CalculateField 城区样点 权利人 Mid( [受让方],4,4 ) VB #</Process><Process ToolSource="c:\program files (x86)\arcgis\desktop10.2\ArcToolbox\Toolboxes\Data Management Tools.tbx\CalculateField" Date="20240109" Time="090901">CalculateField 城区样点 权利人 Mid( [受让方],4,4 ) VB #</Process><Process ToolSource="c:\program files (x86)\arcgis\desktop10.2\ArcToolbox\Toolboxes\Data Management Tools.tbx\CalculateField" Date="20240109" Time="090919">CalculateField 城区样点 权利人 Mid( [受让方],4,4 ) VB #</Process><Process ToolSource="c:\program files (x86)\arcgis\desktop10.2\ArcToolbox\Toolboxes\Data Management Tools.tbx\CalculateField" Date="20240109" Time="090943">CalculateField 城区样点 权利人 "少林机场" VB #</Process><Process ToolSource="c:\program files (x86)\arcgis\desktop10.2\ArcToolbox\Toolboxes\Data Management Tools.tbx\CalculateField" Date="20240109" Time="091014">CalculateField 城区样点 权利人 [受让方] VB #</Process><Process ToolSource="c:\program files (x86)\arcgis\desktop10.2\ArcToolbox\Toolboxes\Data Management Tools.tbx\CalculateField" Date="20240109" Time="091025">CalculateField 城区样点 权利人 [受让方] VB #</Process><Process ToolSource="c:\program files (x86)\arcgis\desktop10.2\ArcToolbox\Toolboxes\Data Management Tools.tbx\CalculateField" Date="20240109" Time="091040">CalculateField 城区样点 权利人 [受让方] VB #</Process><Process ToolSource="c:\program files (x86)\arcgis\desktop10.2\ArcToolbox\Toolboxes\Data Management Tools.tbx\CalculateField" Date="20240109" Time="091115">CalculateField 城区样点 权利人 "少林武校" VB #</Process><Process ToolSource="c:\program files (x86)\arcgis\desktop10.2\ArcToolbox\Toolboxes\Data Management Tools.tbx\CalculateField" Date="20240109" Time="091132">CalculateField 城区样点 权利人 "少林投资" VB #</Process><Process ToolSource="c:\program files (x86)\arcgis\desktop10.2\ArcToolbox\Toolboxes\Data Management Tools.tbx\CalculateField" Date="20250915" Time="105618">CalculateField 城区样点 存量序号 33 VB #</Process><Process ToolSource="c:\program files (x86)\arcgis\desktop10.2\ArcToolbox\Toolboxes\Data Management Tools.tbx\CalculateField" Date="20250915" Time="105905">CalculateField 城区样点 存量序号 33 VB #</Process><Process ToolSource="c:\program files (x86)\arcgis\desktop10.2\ArcToolbox\Toolboxes\Data Management Tools.tbx\CalculateField" Date="20250915" Time="110515">CalculateField 城区样点 存量序号 1 VB #</Process><Process ToolSource="c:\program files (x86)\arcgis\desktop10.2\ArcToolbox\Toolboxes\Data Management Tools.tbx\CalculateField" Date="20250915" Time="110544">CalculateField 城区样点 存量序号 2 VB #</Process><Process ToolSource="c:\program files (x86)\arcgis\desktop10.2\ArcToolbox\Toolboxes\Data Management Tools.tbx\CalculateField" Date="20250915" Time="110555">CalculateField 城区样点 存量序号 45 VB #</Process><Process ToolSource="c:\program files (x86)\arcgis\desktop10.2\ArcToolbox\Toolboxes\Data Management Tools.tbx\CalculateField" Date="20250915" Time="110602">CalculateField 城区样点 存量序号 28 VB #</Process><Process ToolSource="c:\program files (x86)\arcgis\desktop10.2\ArcToolbox\Toolboxes\Data Management Tools.tbx\CalculateField" Date="20250915" Time="110616">CalculateField 城区样点 存量序号 15 VB #</Process><Process ToolSource="c:\program files (x86)\arcgis\desktop10.2\ArcToolbox\Toolboxes\Data Management Tools.tbx\CalculateField" Date="20250915" Time="110623">CalculateField 城区样点 存量序号 16 VB #</Process><Process ToolSource="c:\program files (x86)\arcgis\desktop10.2\ArcToolbox\Toolboxes\Data Management Tools.tbx\CalculateField" Date="20250915" Time="110637">CalculateField 城区样点 存量序号 27 VB #</Process><Process ToolSource="c:\program files (x86)\arcgis\desktop10.2\ArcToolbox\Toolboxes\Data Management Tools.tbx\CalculateField" Date="20250915" Time="110657">CalculateField 城区样点 存量序号 44 VB #</Process><Process ToolSource="c:\program files (x86)\arcgis\desktop10.2\ArcToolbox\Toolboxes\Data Management Tools.tbx\CalculateField" Date="20250915" Time="110718">CalculateField 城区样点 存量序号 17 VB #</Process><Process ToolSource="c:\program files (x86)\arcgis\desktop10.2\ArcToolbox\Toolboxes\Data Management Tools.tbx\CalculateField" Date="20250915" Time="110728">CalculateField 城区样点 存量序号 48 VB #</Process><Process ToolSource="c:\program files (x86)\arcgis\desktop10.2\ArcToolbox\Toolboxes\Data Management Tools.tbx\CalculateField" Date="20250915" Time="110735">CalculateField 城区样点 存量序号 50 VB #</Process><Process ToolSource="c:\program files (x86)\arcgis\desktop10.2\ArcToolbox\Toolboxes\Data Management Tools.tbx\CalculateField" Date="20250915" Time="110741">CalculateField 城区样点 存量序号 26 VB #</Process><Process ToolSource="c:\program files (x86)\arcgis\desktop10.2\ArcToolbox\Toolboxes\Data Management Tools.tbx\CalculateField" Date="20250915" Time="110749">CalculateField 城区样点 存量序号 24 VB #</Process><Process ToolSource="c:\program files (x86)\arcgis\desktop10.2\ArcToolbox\Toolboxes\Data Management Tools.tbx\CalculateField" Date="20250915" Time="110756">CalculateField 城区样点 存量序号 5 VB #</Process><Process ToolSource="c:\program files (x86)\arcgis\desktop10.2\ArcToolbox\Toolboxes\Data Management Tools.tbx\CalculateField" Date="20250915" Time="110859">CalculateField 城区样点 存量序号 4 VB #</Process><Process ToolSource="c:\program files (x86)\arcgis\desktop10.2\ArcToolbox\Toolboxes\Data Management Tools.tbx\CalculateField" Date="20250915" Time="111336">CalculateField 城区样点 存量序号 6 VB #</Process><Process ToolSource="c:\program files (x86)\arcgis\desktop10.2\ArcToolbox\Toolboxes\Data Management Tools.tbx\CalculateField" Date="20250915" Time="111354">CalculateField 城区样点 存量序号 32 VB #</Process><Process ToolSource="c:\program files (x86)\arcgis\desktop10.2\ArcToolbox\Toolboxes\Data Management Tools.tbx\CalculateField" Date="20250915" Time="111404">CalculateField 城区样点 存量序号 33 VB #</Process><Process ToolSource="c:\program files (x86)\arcgis\desktop10.2\ArcToolbox\Toolboxes\Data Management Tools.tbx\CalculateField" Date="20250915" Time="111415">CalculateField 城区样点 存量序号 7 VB #</Process><Process ToolSource="c:\program files (x86)\arcgis\desktop10.2\ArcToolbox\Toolboxes\Data Management Tools.tbx\CalculateField" Date="20250915" Time="111435">CalculateField 城区样点 存量序号 36 VB #</Process><Process ToolSource="c:\program files (x86)\arcgis\desktop10.2\ArcToolbox\Toolboxes\Data Management Tools.tbx\CalculateField" Date="20250915" Time="111510">CalculateField 城区样点 存量序号 37 VB #</Process><Process ToolSource="c:\program files (x86)\arcgis\desktop10.2\ArcToolbox\Toolboxes\Data Management Tools.tbx\CalculateField" Date="20250915" Time="111518">CalculateField 城区样点 存量序号 38 VB #</Process><Process ToolSource="c:\program files (x86)\arcgis\desktop10.2\ArcToolbox\Toolboxes\Data Management Tools.tbx\CalculateField" Date="20250915" Time="111526">CalculateField 城区样点 存量序号 39 VB #</Process><Process ToolSource="c:\program files (x86)\arcgis\desktop10.2\ArcToolbox\Toolboxes\Data Management Tools.tbx\CalculateField" Date="20250915" Time="111617">CalculateField 城区样点 存量序号 13 VB #</Process><Process ToolSource="c:\program files (x86)\arcgis\desktop10.2\ArcToolbox\Toolboxes\Data Management Tools.tbx\CalculateField" Date="20250915" Time="111728">CalculateField 城区样点 存量序号 34 VB #</Process><Process ToolSource="c:\program files (x86)\arcgis\desktop10.2\ArcToolbox\Toolboxes\Data Management Tools.tbx\CalculateField" Date="20250915" Time="145635">CalculateField 城区样点 地块编号 "登政出〔2023〕8号（网）" VB #</Process><Process ToolSource="c:\program files (x86)\arcgis\desktop10.2\ArcToolbox\Toolboxes\Data Management Tools.tbx\CalculateField" Date="20250915" Time="150043">CalculateField 城区样点 地块编号 "登政出〔2022〕20号（网）" VB #</Process><Process ToolSource="c:\program files (x86)\arcgis\desktop10.2\ArcToolbox\Toolboxes\Data Management Tools.tbx\CalculateField" Date="20250915" Time="150105">CalculateField 城区样点 权利人 "河南派基实业" VB #</Process><Process ToolSource="c:\program files (x86)\arcgis\desktop10.2\ArcToolbox\Toolboxes\Data Management Tools.tbx\CalculateField" Date="20250915" Time="150120">CalculateField 城区样点 年份 "2024年" VB #</Process><Process ToolSource="c:\program files (x86)\arcgis\desktop10.2\ArcToolbox\Toolboxes\Data Management Tools.tbx\CalculateField" Date="20250915" Time="150133">CalculateField 城区样点 用途4 "住宅" VB #</Process><Process ToolSource="c:\program files (x86)\arcgis\desktop10.2\ArcToolbox\Toolboxes\Data Management Tools.tbx\CalculateField" Date="20250915" Time="150211">CalculateField 城区样点 成交价万元 254 VB #</Process><Process ToolSource="c:\program files (x86)\arcgis\desktop10.2\ArcToolbox\Toolboxes\Data Management Tools.tbx\CalculateField" Date="20250915" Time="150229">CalculateField 城区样点 容积率2 1.9 VB #</Process><Process ToolSource="c:\program files (x86)\arcgis\desktop10.2\ArcToolbox\Toolboxes\Data Management Tools.tbx\CalculateField" Date="20250915" Time="150607">CalculateField 城区样点 地块编号 "登政出〔2024〕2号（网）" VB #</Process><Process ToolSource="c:\program files (x86)\arcgis\desktop10.2\ArcToolbox\Toolboxes\Data Management Tools.tbx\CalculateField" Date="20250915" Time="150623">CalculateField 城区样点 年份 "2024年" VB #</Process><Process ToolSource="c:\program files (x86)\arcgis\desktop10.2\ArcToolbox\Toolboxes\Data Management Tools.tbx\CalculateField" Date="20250915" Time="150645">CalculateField 城区样点 容积率2 1.8 VB #</Process><Process ToolSource="c:\program files (x86)\arcgis\desktop10.2\ArcToolbox\Toolboxes\Data Management Tools.tbx\CalculateField" Date="20250915" Time="150700">CalculateField 城区样点 成交价万元 250 VB #</Process><Process Name="删除字段" ToolSource="c:\program files (x86)\arcgis\desktop10.2\ArcToolbox\Toolboxes\Data Management Tools.tbx\DeleteField" Date="20260102" Time="203645">DeleteField 住宅样点 Id;序号;BH;面积0;OID_;OBJECTID;序号_1;地块编号;批次名称;批准文号;受让方;储备面积亩;供应面积平;供应面积亩;用_途;供地_方式;地下空间平;道路平方米;绿地平方米;项目名;储备地块编;占用面积（;剩余</Process><Process Name="删除字段" ToolSource="c:\program files (x86)\arcgis\desktop10.2\ArcToolbox\Toolboxes\Data Management Tools.tbx\DeleteField" Date="20260103" Time="145436">DeleteField 住宅样点 成交_时间;评估价万元;成交单价万;挂牌起始价;成交总价万;备注;容积率;建筑密度（;绿地率（_;建筑高度（;投资总额;XH;用途;存量序号</Process></lineage></DataProperties></Esri></metadata>
